awmt/proto_dsp_tools/__init__.py
awmt/proto_dsp_tools/example.py
awmt_proto_dsp_tools-0.1.0.dist-info/LICENSE
awmt_proto_dsp_tools-0.1.0.dist-info/METADATA
awmt_proto_dsp_tools-0.1.0.dist-info/WHEEL
awmt_proto_dsp_tools-0.1.0.dist-info/RECORD
